LICENSE
README.rst
setup.py
longmao/__init__.py
longmao/api/Api.py
longmao/api/__init__.py
longmao/api/tags/ApiTagsDeleteCsv.py
longmao/api/tags/ApiTagsUploadCsv.py
longmao/api/tags/__init__.py
longmao/core/DefaultLongMaoClient.py
longmao/core/LongMaoClientConfig.py
longmao/core/__init__.py
longmao/core/exception/Exception.py
longmao/core/exception/__init__.py
longmao/core/http/FileItem.py
longmao/core/http/HttpRequest.py
longmao/core/http/__init__.py
longmao/core/utils/CommonUtils.py
longmao/core/utils/Constants.py
longmao/core/utils/SignatureUtils.py
longmao/core/utils/StringUtils.py
longmao/core/utils/__init__.py
longmao_open_sdk_python.egg-info/PKG-INFO
longmao_open_sdk_python.egg-info/SOURCES.txt
longmao_open_sdk_python.egg-info/dependency_links.txt
longmao_open_sdk_python.egg-info/requires.txt
longmao_open_sdk_python.egg-info/top_level.txt