Metadata-Version: 2.1
Name: longmao-open-sdk-python
Version: 0.1.6
Summary: The official LongMao SDK for Python.
Home-page: https://github.com/nayuan/longmao-open-sdk-python
Author: nayuan
Author-email: haojunsheng@longmaosoft.com
License: Apache
Keywords: longmao,open,sdk
Platform: any
Classifier: Intended Audience :: Developers
Classifier: License :: OSI Approved :: Apache Software License
Classifier: Programming Language :: Python
Classifier: Programming Language :: Python :: 2.6
Classifier: Programming Language :: Python :: 2.7
Classifier: Programming Language :: Python :: 3
Classifier: Programming Language :: Python :: 3.3
Classifier: Topic :: Software Development
License-File: LICENSE
